audiorecorder/__init__.py
audiorecorder/frontend/build/asset-manifest.json
audiorecorder/frontend/build/bootstrap.min.css
audiorecorder/frontend/build/index.html
audiorecorder/frontend/build/static/js/34.bb54d4a5.chunk.js
audiorecorder/frontend/build/static/js/34.bb54d4a5.chunk.js.map
audiorecorder/frontend/build/static/js/937.02c36243.chunk.js
audiorecorder/frontend/build/static/js/937.02c36243.chunk.js.map
audiorecorder/frontend/build/static/js/main.03309faa.js
audiorecorder/frontend/build/static/js/main.03309faa.js.LICENSE.txt
audiorecorder/frontend/build/static/js/main.03309faa.js.map
streamlit_audiorecorder-0.0.6.dist-info/LICENSE
streamlit_audiorecorder-0.0.6.dist-info/METADATA
streamlit_audiorecorder-0.0.6.dist-info/WHEEL
streamlit_audiorecorder-0.0.6.dist-info/top_level.txt
streamlit_audiorecorder-0.0.6.dist-info/RECORD
