Metadata-Version: 2.1
Name: streamlit-audiorecorder
Version: 0.0.6
Summary: Audio recorder component for streamlit
Home-page: https://github.com/theevann/streamlit-audiorecorder
Author: Evann Courdier
Author-email: 
Requires-Python: >=3.6
License-File: LICENSE
Requires-Dist: streamlit>=0.63
Requires-Dist: pydub>=0.24
